Metadata-Version: 2.1
Name: pyChatGPT-intl
Version: 0.0.5
Summary: This Python3 module acts as a wrapper for ChatGPT API and will help you to use ChatGPT in your own language.
Home-page: https://github.com/asirihewage/pyChatGPT-intl
Author: Asiri Hewage
License: GNU General Public License v3 (GPLv3)
Platform: UNKNOWN
Classifier: Development Status :: 4 - Beta
Classifier: Environment :: Console
Classifier: Intended Audience :: Developers
Classifier: License :: OSI Approved :: GNU General Public License v3 (GPLv3)
Classifier: Operating System :: POSIX :: Linux
Classifier: Programming Language :: Python :: 3.6
Classifier: Programming Language :: Python :: Implementation :: PyPy
Classifier: Topic :: Software Development :: Libraries :: Python Modules
Requires-Python: >=3.6
License-File: LICENSE
